Workbook

Sheet Dashboard
A1: SiteSentry Financial Dashboard
A3: Market | D3: Beachhead
A4: Global smart PPE market | B4: ='Market Sizing'!B13&"M" | D4: Beachhead end users | E4: ='Market Sizing'!B5
A5: Smart PPE CAGR | B5: ='Market Sizing'!B15 | D5: 100% beachhead software ARR | E5: ='Market Sizing'!B6
A6: Global smart helmet market | B6: ='Market Sizing'!B16&"M" | D6: Year 3 SOM active users | E6: ='Market Sizing'!B11
A7: Smart helmet CAGR | B7: ='Market Sizing'!B18 | D7: Year 3 ARR | E7: ='Annual Outlook'!D16
A10: Year 1 | D10: 3-Year Outlook
A11: Year 1 revenue | B11: ='Annual Outlook'!B9 | D11: Year 2 revenue | E11: ='Annual Outlook'!C9
A12: Year 1 gross margin | B12: ='Annual Outlook'!B12 | D12: Year 2 revenue growth | E12: ='Annual Outlook'!C15
A13: Year-end ARR | B13: ='Annual Outlook'!B16 | D13: Year 3 revenue | E13: ='Annual Outlook'!D9
A14: Net cash impact | B14: ='Monthly P&L'!N18 | D14: Year 3 gross margin | E14: ='Annual Outlook'!D12

Sheet Assumptions
A1: Category | B1: Variable | C1: Value | D1: Notes
A2: Pricing | B2: Hardware price per unit | C2: 1800 | D2: Pilot-stage sale price in CAD
A3: Pricing | B3: Monthly software fee per active user | C3: 85 | D3: Per-user SaaS fee
A4: Pricing | B4: Onboarding fee per new customer | C4: 7500 | D4: Setup and training
A5: COGS | B5: Hardware COGS per unit | C5: 1050 | D5: Electronics, assembly, shipping
A6: COGS | B6: Cloud cost per active user per month | C6: 12 | D6: Inference, storage, compute
A7: COGS | B7: Support cost per active user per month | C7: 8 | D7: Customer support and success
A8: OPEX | B8: Engineering payroll per month | C8: 18000 | D8: ML plus embedded/product contractor mix
A9: OPEX | B9: Sales and business development per month | C9: 7000 | D9: Founder sales plus travel
A10: OPEX | B10: Software/tools/admin per month | C10: 2500 | D10: SaaS, insurance, legal, admin
A11: OPEX | B11: Marketing/events per month | C11: 1500 | D11: Industry events and outreach
A12: CAPEX | B12: Prototype and test equipment | C12: 45000 | D12: Spread across the first 4 months
A13: Market | B13: Global smart PPE market size, 2025 (USD M) | C13: 3300 | D13: From team status report market citation
... A24: Growth | B24: Year 3 OPEX growth | C24: 0.2 | D24: Scaling operations

Sheet Deployment Plan
A1: Metric | B1: M1 | C1: M2 | D1: M3 | E1: M4 | F1: M5 | G1: M6 | H1: M7 | I1: M8 | J1: M9 | K1: M10 | L1: M11 | M1: M12 | N1: Year 1 Total
A2: New customers | B2: 0 | C2: 0 | D2: 0 | E2: 0 | F2: 0 | G2: 1 | H2: 0 | I2: 1 | J2: 0 | K2: 1 | L2: 0 | M2: 1 | N2: =SUM(B2:M2)
A3: New hardware units | B3: 0 | C3: 0 | D3: 0 | E3: 0 | F3: 0 | G3: 20 | H3: 0 | I3: 30 | J3: 0 | K3: 40 | L3: 0 | M3: 60 | N3: =SUM(B3:M3)
A4: Active users | B4: 0 | C4: 0 | D4: 0 | E4: 0 | F4: 0 | G4: 20 | H4: 20 | I4: 50 | J4: 50 | K4: 90 | L4: 90 | M4: 150 | N4: =SUM(B4:M4)

Sheet Monthly P&L
A1: Line Item | B1: M1 | C1: M2 | D1: M3 | E1: M4 | F1: M5 | G1: M6 | H1: M7 | I1: M8 | J1: M9 | K1: M10 | L1: M11 | M1: M12 | N1: Year 1 Total
A2: Hardware revenue | B2: ='Deployment Plan'!B3*'Assumptions'!C2 | C2: ='Deployment Plan'!C3*'Assumptions'!C2 | D2: ='Deployment Plan'!D3*'Assumptions'!C2 | E2: ='Deployment Plan'!E3*'Assumptions'!C2 | F2: ='Deployment Plan'!F3*'Assumptions'!C2 | G2: ='Deployment Plan'!G3*'Assumptions'!C2 | H2: ='Deployment Plan'!H3*'Assumptions'!C2 | I2: ='Deployment Plan'!I3*'Assumptions'!C2 | J2: ='Deployment Plan'!J3*'Assumptions'!C2 | K2: ='Deployment Plan'!K3*'Assumptions'!C2 | L2: ='Deployment Plan'!L3*'Assumptions'!C2 | M2: ='Deployment Plan'!M3*'Assumptions'!C2 | N2: =SUM(B2:M2)
A3: Software revenue | B3: ='Deployment Plan'!B4*'Assumptions'!C3 | C3: ='Deployment Plan'!C4*'Assumptions'!C3 | D3: ='Deployment Plan'!D4*'Assumptions'!C3 | E3: ='Deployment Plan'!E4*'Assumptions'!C3 | F3: ='Deployment Plan'!F4*'Assumptions'!C3 | G3: ='Deployment Plan'!G4*'Assumptions'!C3 | H3: ='Deployment Plan'!H4*'Assumptions'!C3 | I3: ='Deployment Plan'!I4*'Assumptions'!C3 | J3: ='Deployment Plan'!J4*'Assumptions'!C3 | K3: ='Deployment Plan'!K4*'Assumptions'!C3 | L3: ='Deployment Plan'!L4*'Assumptions'!C3 | M3: ='Deployment Plan'!M4*'Assumptions'!C3 | N3: =SUM(B3:M3)
A4: Onboarding revenue | B4: ='Deployment Plan'!B2*'Assumptions'!C4 | C4: ='Deployment Plan'!C2*'Assumptions'!C4 | D4: ='Deployment Plan'!D2*'Assumptions'!C4 | E4: ='Deployment Plan'!E2*'Assumptions'!C4 | F4: ='Deployment Plan'!F2*'Assumptions'!C4 | G4: ='Deployment Plan'!G2*'Assumptions'!C4 | H4: ='Deployment Plan'!H2*'Assumptions'!C4 | I4: ='Deployment Plan'!I2*'Assumptions'!C4 | J4: ='Deployment Plan'!J2*'Assumptions'!C4 | K4: ='Deployment Plan'!K2*'Assumptions'!C4 | L4: ='Deployment Plan'!L2*'Assumptions'!C4 | M4: ='Deployment Plan'!M2*'Assumptions'!C4 | N4: =SUM(B4:M4)
A5: Total revenue | B5: =SUM(B2:B4) | C5: =SUM(C2:C4) | D5: =SUM(D2:D4) | E5: =SUM(E2:E4) | F5: =SUM(F2:F4) | G5: =SUM(G2:G4) | H5: =SUM(H2:H4) | I5: =SUM(I2:I4) | ... M5: =SUM(M2:M4) | N5: =SUM(B5:M5)
A6: Hardware COGS | B6: ='Deployment Plan'!B3*'Assumptions'!C5 | C6: ='Deployment Plan'!C3*'Assumptions'!C5 | D6: ='Deployment Plan'!D3*'Assumptions'!C5 | E6: ='Deployment Plan'!E3*'Assumptions'!C5 | F6: ='Deployment Plan'!F3*'Assumptions'!C5 | G6: ='Deployment Plan'!G3*'Assumptions'!C5 | H6: ='Deployment Plan'!H3*'Assumptions'!C5 | I6: ='Deployment Plan'!I3*'Assumptions'!C5 | J6: ='Deployment Plan'!J3*'Assumptions'!C5 | K6: ='Deployment Plan'!K3*'Assumptions'!C5 | L6: ='Deployment Plan'!L3*'Assumptions'!C5 | M6: ='Deployment Plan'!M3*'Assumptions'!C5 | N6: =SUM(B6:M6)
A7: Cloud cost | B7: ='Deployment Plan'!B4*'Assumptions'!C6 | C7: ='Deployment Plan'!C4*'Assumptions'!C6 | D7: ='Deployment Plan'!D4*'Assumptions'!C6 | E7: ='Deployment Plan'!E4*'Assumptions'!C6 | F7: ='Deployment Plan'!F4*'Assumptions'!C6 | G7: ='Deployment Plan'!G4*'Assumptions'!C6 | H7: ='Deployment Plan'!H4*'Assumptions'!C6 | I7: ='Deployment Plan'!I4*'Assumptions'!C6 | J7: ='Deployment Plan'!J4*'Assumptions'!C6 | K7: ='Deployment Plan'!K4*'Assumptions'!C6 | L7: ='Deployment Plan'!L4*'Assumptions'!C6 | M7: ='Deployment Plan'!M4*'Assumptions'!C6 | N7: =SUM(B7:M7)
A8: Support cost | B8: ='Deployment Plan'!B4*'Assumptions'!C7 | C8: ='Deployment Plan'!C4*'Assumptions'!C7 | D8: ='Deployment Plan'!D4*'Assumptions'!C7 | E8: ='Deployment Plan'!E4*'Assumptions'!C7 | F8: ='Deployment Plan'!F4*'Assumptions'!C7 | G8: ='Deployment Plan'!G4*'Assumptions'!C7 | H8: ='Deployment Plan'!H4*'Assumptions'!C7 | I8: ='Deployment Plan'!I4*'Assumptions'!C7 | J8: ='Deployment Plan'!J4*'Assumptions'!C7 | K8: ='Deployment Plan'!K4*'Assumptions'!C7 | L8: ='Deployment Plan'!L4*'Assumptions'!C7 | M8: ='Deployment Plan'!M4*'Assumptions'!C7 | N8: =SUM(B8:M8)
A9: Total COGS | B9: =SUM(B6:B8) | C9: =SUM(C6:C8) | D9: =SUM(D6:D8) | E9: =SUM(E6:E8) | F9: =SUM(F6:F8) | G9: =SUM(G6:G8) | H9: =SUM(H6:H8) | I9: =SUM(I6:I8) | ... M9: =SUM(M6:M8) | N9: =SUM(B9:M9)
A10: Gross profit | B10: =B5-B9 | C10: =C5-C9 | D10: =D5-D9 | E10: =E5-E9 | F10: =F5-F9 | G10: =G5-G9 | H10: =H5-H9 | I10: =I5-I9 | ... M10: =M5-M9 | N10: =SUM(B10:M10)
A11: Engineering payroll | B11: ='Assumptions'!C8 | C11: ='Assumptions'!C8 | D11: ='Assumptions'!C8 | E11: ='Assumptions'!C8 | F11: ='Assumptions'!C8 | G11: ='Assumptions'!C8 | H11: ='Assumptions'!C8 | I11: ='Assumptions'!C8 | J11: ='Assumptions'!C8 | K11: ='Assumptions'!C8 | L11: ='Assumptions'!C8 | M11: ='Assumptions'!C8 | N11: =SUM(B11:M11)
A12: Sales and business development | B12: ='Assumptions'!C9 | C12: ='Assumptions'!C9 | D12: ='Assumptions'!C9 | E12: ='Assumptions'!C9 | F12: ='Assumptions'!C9 | G12: ='Assumptions'!C9 | H12: ='Assumptions'!C9 | I12: ='Assumptions'!C9 | J12: ='Assumptions'!C9 | K12: ='Assumptions'!C9 | L12: ='Assumptions'!C9 | M12: ='Assumptions'!C9 | N12: =SUM(B12:M12)
A13: Software/tools/admin | B13: ='Assumptions'!C10 | C13: ='Assumptions'!C10 | D13: ='Assumptions'!C10 | E13: ='Assumptions'!C10 | F13: ='Assumptions'!C10 | G13: ='Assumptions'!C10 | H13: ='Assumptions'!C10 | I13: ='Assumptions'!C10 | J13: ='Assumptions'!C10 | K13: ='Assumptions'!C10 | L13: ='Assumptions'!C10 | M13: ='Assumptions'!C10 | N13: =SUM(B13:M13)
A14: Marketing/events | B14: ='Assumptions'!C11 | C14: ='Assumptions'!C11 | D14: ='Assumptions'!C11 | E14: ='Assumptions'!C11 | F14: ='Assumptions'!C11 | G14: ='Assumptions'!C11 | H14: ='Assumptions'!C11 | I14: ='Assumptions'!C11 | J14: ='Assumptions'!C11 | K14: ='Assumptions'!C11 | L14: ='Assumptions'!C11 | M14: ='Assumptions'!C11 | N14: =SUM(B14:M14)
A15: Total OPEX | B15: =SUM(B11:B14) | C15: =SUM(C11:C14) | D15: =SUM(D11:D14) | E15: =SUM(E11:E14) | F15: =SUM(F11:F14) | G15: =SUM(G11:G14) | H15: =SUM(H11:H14) | I15: =SUM(I11:I14) | ... M15: =SUM(M11:M14) | N15: =SUM(B15:M15)
A16: EBITDA before CAPEX | B16: =B10-B15 | C16: =C10-C15 | D16: =D10-D15 | E16: =E10-E15 | F16: =F10-F15 | G16: =G10-G15 | H16: =H10-H15 | I16: =I10-I15 | ... M16: =M10-M15 | N16: =SUM(B16:M16)
A17: CAPEX | B17: 11250 | C17: 11250 | D17: 11250 | E17: 11250 | F17: 0 | G17: 0 | H17: 0 | I17: 0 | J17: 0 | K17: 0 | L17: 0 | M17: 0 | N17: =SUM(B17:M17)
A18: Net cash impact | B18: =B16-B17 | C18: =C16-C17 | D18: =D16-D17 | E18: =E16-E17 | F18: =F16-F17 | G18: =G16-G17 | H18: =H16-H17 | I18: =I16-I17 | ... M18: =M16-M17 | N18: =SUM(B18:M18)

Sheet Unit Economics
A1: Metric | B1: Value | C1: Formula / Comment
A2: Hardware gross margin per unit | B2: ='Assumptions'!C2-'Assumptions'!C5 | C2: Hardware price minus hardware COGS
A3: Monthly contribution per active user | B3: ='Assumptions'!C3-'Assumptions'!C6-'Assumptions'!C7 | C3: Software fee minus support and cloud
A4: First-year customers | B4: ='Deployment Plan'!N2 | C4: New customers in year 1
A5: First-year hardware units | B5: ='Deployment Plan'!N3 | C5: Total deployed pilot units
A6: Year-end active users | B6: =MROUND('Deployment Plan'!M4,1) | C6: Active users in month 12
A7: Average onboarding revenue per customer | B7: ='Assumptions'!C4 | C7: One-time fee
A8: Year 1 gross margin | B8: ='Monthly P&L'!N10/'Monthly P&L'!N5 | C8: Gross profit divided by total revenue
A9: Year-end ARR | B9: ='Deployment Plan'!M4*'Assumptions'!C3*12 | C9: Annual recurring software revenue exiting year 1

Sheet Market Sizing
A1: Metric | B1: Value | C1: Notes
A2: Beachhead geography | B2: Western Canada industrial construction and turnaround sites | C2: Initial focus
A3: Target organizations in beachhead | B3: ='Assumptions'!C17 | C3: Planning assumption to be validated
A4: Average qualifying workers per target org | B4: ='Assumptions'!C18 | C4: Workers in high-risk dynamic environments
A5: Total beachhead end users | B5: =B3*B4 | C5: Potential wearable users
A6: Annual software revenue at 100% beachhead penetration | B6: =B5*'Assumptions'!C3*12 | C6: ARR only, excludes hardware
A7: Illustrative Year 2 SOM penetration | B7: ='Assumptions'!C19 | C7: Base-case SOM assumption
A8: Illustrative Year 2 active users | B8: =B5*B7 | C8: Users at Year 2 SOM
A9: Illustrative Year 2 ARR | B9: =B8*'Assumptions'!C3*12 | C9: Software ARR at Year 2 SOM
A10: Illustrative Year 3 SOM penetration | B10: ='Assumptions'!C20 | C10: Attainable share after validation
A11: Illustrative Year 3 active users | B11: =B5*B10 | C11: Users at Year 3 SOM
A12: Illustrative Year 3 ARR | B12: =B11*'Assumptions'!C3*12 | C12: Software ARR at Year 3 SOM
A13: Global smart PPE market size, 2025 (USD M) | B13: ='Assumptions'!C13 | C13: Top-down market context
A14: Global smart PPE market size, 2033 (USD M) | B14: ='Assumptions'!C14 | C14: Top-down market context
A15: Global smart PPE market CAGR | B15: =(B14/B13)^(1/8)-1 | C15: 2025 to 2033 CAGR
A16: Global smart helmet market size, 2024 (USD M) | B16: ='Assumptions'!C15 | C16: Top-down market context
A17: Global smart helmet market size, 2030 (USD M) | B17: ='Assumptions'!C16 | C17: Top-down market context
A18: Global smart helmet market CAGR | B18: =(B17/B16)^(1/6)-1 | C18: 2024 to 2030 CAGR

Sheet Annual Outlook
A1: Metric | B1: Year 1 | C1: Year 2 | D1: Year 3
A2: New customers | B2: ='Deployment Plan'!N2 | C2: ='Assumptions'!C21 | D2: ='Assumptions'!C22
A3: New hardware units | B3: ='Deployment Plan'!N3 | C3: =ROUND('Market Sizing'!B8-'Deployment Plan'!M4,0) | D3: =ROUND('Market Sizing'!B11-'Market Sizing'!B8,0)
A4: Year-end active users | B4: ='Deployment Plan'!M4 | C4: =ROUND('Market Sizing'!B8,0) | D4: =ROUND('Market Sizing'!B11,0)
A5: Average active users | B5: ='Deployment Plan'!N4/12 | C5: =(B4+C4)/2 | D5: =(C4+D4)/2
A6: Hardware revenue | B6: ='Monthly P&L'!N2 | C6: =C2*'Assumptions'!C2 | D6: =D2*'Assumptions'!C2
A7: Software revenue | B7: ='Monthly P&L'!N3 | C7: =C4*12*'Assumptions'!C3 | D7: =D4*12*'Assumptions'!C3
A8: Onboarding revenue | B8: ='Monthly P&L'!N4 | C8: =C2*'Assumptions'!C4 | D8: =D2*'Assumptions'!C4
A9: Total revenue | B9: ='Monthly P&L'!N5 | C9: =SUM(C6:C8) | D9: =SUM(D6:D8)
A10: Total COGS | B10: ='Monthly P&L'!N9 | C10: =(C2*'Assumptions'!C5)+(C4*12*('Assumptions'!C6+'Assumptions'!C7)) | D10: =(D2*'Assumptions'!C5)+(D4*12*('Assumptions'!C6+'Assumptions'!C7))
A11: Gross profit | B11: ='Monthly P&L'!N10 | C11: =C9-C10 | D11: =D9-D10
A12: Gross margin | B12: ='Monthly P&L'!N10/'Monthly P&L'!N5 | C12: =C11/C9 | D12: =D11/D9
A13: OPEX | B13: ='Monthly P&L'!N15 | C13: =B13*(1+'Assumptions'!C23) | D13: =C13*(1+'Assumptions'!C24)
A14: EBITDA before CAPEX | B14: ='Monthly P&L'!N16 | C14: =C11-C13 | D14: =D11-D13
A15: Revenue growth | C15: =C9/B9-1 | D15: =D9/C9-1
A16: Year-end ARR | B16: ='Deployment Plan'!M4*'Assumptions'!C3*12 | C16: =C3*'Assumptions'!C3*12 | D16: =D3*'Assumptions'!C3*12

Sheet Milestones
A1: Year | B1: Milestones
A2: Year 1 | B2: Build MVP, secure 4 paid pilots, validate one or two hazard classes, collect field data
A3: Year 2 | B3: Convert pilots to annual contracts, improve product reliability, establish reference customers
A4: Year 3 | B4: Expand into mining or manufacturing, add channel partners, grow recurring software base
A5: Years 4-5 | B5: Broaden supported hazard library, integrate with enterprise safety workflows, win multi-site deployments
